{
  "$schema": "../../../../aux_schema.json",
  "name": "RuinsIsle",
  "rooms": [
    {
      "name": "TopLeft",
      "chests": [
        {
          "name": "Underwater",
          "type": "chest",
          "contents": "power_gem",
          "zmb_file_path": "TODO",
          "zmb_mapobject_index": 0
        }
      ],
      "doors": [
        {
          "name": "ToSouthRight",
          "link": "BottomLeft.AboveMaze.ToNorthRight"
        },
        {
          "name": "ToSouthLeft",
          "link": "BottomLeft.ToNorthLeft.ToNorthLeft"
        },
        {
          "name": "ToBremeurPyramid",
          "link": "BremeurPyramid.F1.Main.Exit"
        },
        {
          "name": "ToEastBottom",
          "link": "TopRight.FromWest.ToWestBottom"
        },
        {
          "name": "ToSouthShortcut",
          "link": "BottomLeft.AboveCave.ToNorthShortcut"
        },
        {
          "name": "ToEastTop",
          "link": "TopRight.Main.ToWestTop"
        },
        {
          "name": "ToSouthUnderwater",
          "link": "BottomLeft.Underwater.ToNorthUnderwater"
        },
        {
          "name": "ToEastUnderwaterTop",
          "link": "TopRight.Underwater.ToWestUnderwaterTop"
        },
        {
          "name": "ToEastUnderwaterBottom",
          "link": "TopRight.Underwater.ToWestUnderwaterBottom"
        },
        {
          "name": "ToUnderwaterCave",
          "link": "UnderwaterCave.Main.Exit"
        }
      ]
    }
  ]
}
